[
  {
    "id": 1,
    "name": "Gin Rickey",
    "recipeCategory": "Alcoólico",
    "keywords": [
      "Refrescante"
    ],
    "serveIn": "Copo",
    "recipeCuisine": "Estados Unidos",
    "recipeIngredient": [
      "1 ½ dose de gin",
      "½ dose de suco de limão",
      "⅓ dose de xarope simples",
      "Club Soda ou Água com Gás",
      "1 fatia de limão",
      "Cubos de gelo"
    ],
    "notes": [],
    "recipeInstructions": [
      "Coloque gelo até a metade de uma coqueteleira.",
      "Adicione o gin, o suco de limão e o xarope simples.",
      "Agite bem e coe pelo strainer no copo cheio de gelo.",
      "Complete com a Club Soda ou a água com gás e adicione a fatia de limão."
    ],
    "image": "gin_rickey.jpg"
  },
  {
    "id": 2,
    "name": "Dry Martini",
    "recipeCategory": "Alcoólico",
    "keywords": [
      "Clássico",
      "Forte",
      "Seco",
      "Gelado"
    ],
    "serveIn": "Taça De Coquetel",
    "recipeCuisine": "Estados Unidos",
    "recipeIngredient": [
      "2 doses de gin",
      "3 gotas de vermute seco",
      "cubos de gelo",
      "azeitonas verdes",
      "casca de limão siciliano"
    ],
    "notes": [],
    "recipeInstructions": [
      "Coloque gelo até a metade do mixing glass.",
      "Pingue três gotas de vermute seco sobre o gelo e misture levemente com uma colher bailarina.",
      "Em seguida, acrescente o gin e mexa novamente durante cerca de dez segundos, até que os líquidos estejam bem gelados.",
      "Coe pelo strainer, despejando apenas o líquido na taça.",
      "Passe um pedaço de casca de limão siciliano na borda da taça, apenas para deixar seu perfume.",
      "Espete de uma a três azeitonas verdes em um palito, coloque dentro da taça e sirva imediatamente."
    ],
    "image": "dry_martini.jpg"
  },
  {
    "id": 3,
    "name": "Brandy Alexander",
    "recipeCategory": "Alcoólico",
    "keywords": [
      "Clássico",
      "Cremoso"
    ],
    "serveIn": "Taça De Coquetel",
    "recipeCuisine": "",
    "recipeIngredient": [
      "2 doses de conhaque",
      "2 doses de licor de cacau",
      "2 doses de creme de leite",
      "Cubos de gelo",
      "noz-moscada (para polvilhar)"
    ],
    "notes": [],
    "recipeInstructions": [
      "Coloque de 3 a 5 pedras de gelo numa coqueteleira.",
      "Adicione o conhaque e o licor de cacau.",
      "Acrescente o creme de leite por último.",
      "Agite bem por cerca de 10 segundos, até que a mistura fique bem gelada.",
      "Coe com o strainer, despejando apenas o conteúdo na taça.",
      "Polvilhe a noz-moscada ralando-a por cima."
    ],
    "image": "brandy_alexander.jpg"
  },
  {
    "id": 4,
    "name": "Amarula Ginger",
    "recipeCategory": "Alcoólico",
    "keywords": [
      "Cremoso"
    ],
    "serveIn": "Taça De Coquetel",
    "recipeCuisine": "",
    "recipeIngredient": [
      "60ml de amarula cream",
      "45ml de xarope de gengibre",
      "Cubos de gelo"
    ],
    "notes": [],
    "recipeInstructions": [
      "Encha uma coqueteleira com gelo.",
      "Adicione a Amarula Cream e o xarope de gengibre.",
      "Agite bem e coe pelo strainer, despejando somente o líquido na taça."
    ],
    "image": "amarula_ginger.jpg"
  },
  {
    "id": 5,
    "name": "Amore Vietato",
    "recipeCategory": "Alcoólico",
    "keywords": [
      "Forte",
      "Doce"
    ],
    "serveIn": "Taça De Coquetel",
    "recipeCuisine": "",
    "recipeIngredient": [
      "2 doses de gin",
      "1 dose de suco de toranja",
      "Algumas gotas de xarope simples",
      "2 morangos",
      "1 pepino para decorar",
      "Cubos de gelo"
    ],
    "notes": [],
    "recipeInstructions": [
      "Coloque até metade da coqueteleira de gelo.",
      "Acrescente os morangos e as gotas de xarope simples.",
      "Adicione o gin e por fim o suco de toranja.",
      "Agite bem e coe com o strainer, despejando apenas o líquido na taça.",
      "Coloque morangos fatiados dentro do drink.",
      "Decore com espirais da casca de pepino e corações feitos da casca da toranja."
    ],
    "image": "amore_vietato.jpg"
  },
  {
    "id": 6,
    "name": "Aperol Spritz",
    "recipeCategory": "Alcoólico",
    "keywords": [
      "Amargo",
      "Refrescante"
    ],
    "serveIn": "Taça",
    "recipeCuisine": "Itália",
    "recipeIngredient": [
      "3 doses de prosecco",
      "2 doses de aperol",
      "1 dose de água com gás",
      "1 laranja",
      "Cubos de gelo"
    ],
    "notes": [],
    "recipeInstructions": [
      "Coloque o gelo na taça e adicione o prosecco.",
      "Acrescente o Aperol e em seguida a água com gás.",
      "Mexa levemente com uma colher bailarina e coloque meia fatia de laranja dentro."
    ],
    "image": "aperol_spritz.jpg"
  },
  {
    "id": 7,
    "name": "Apple Cider Soda",
    "recipeCategory": "",
    "keywords": [
      "Doce",
      "Refrescante"
    ],
    "serveIn": "Copo",
    "recipeCuisine": "",
    "recipeIngredient": [
      "250 ml de suco de maçã",
      "1 laranja cortada em fatias",
      "5 palitos de canela em pau",
      "1 gengibre pequeno, picado com a casca.",
      "500 ml de água com Gás",
      "Cubos de gelo"
    ],
    "notes": [],
    "recipeInstructions": [
      "Em uma panela, ferva o suco de maçã, a laranja picada em pedaços, o gengibre e a canela.",
      "Diminua o fogo e deixe cozinhar por 30 minutos em fogo baixo.",
      "Quando estiver pronto, espere esfriar, coloque em uma jarra e deixe resfriar na geladeira por 10 minutos.",
      "Ao servir, coloque gelo até a metade do copo e adicione 100ml de água com Gás.",
      "Acrescente 50 ml da cidra de maçã e decore com meia fatia de laranja e um palito de canela em pau."
    ],
    "image": "apple_cider_soda.jpg"
  },
  {
    "id": 8,
    "name": "Appleberry",
    "recipeCategory": "Alcoólico",
    "keywords": [
      "Doce",
      "Refrescante"
    ],
    "serveIn": "Copo",
    "recipeCuisine": "",
    "recipeIngredient": [
      "1 dose de Bacardi big apple",
      "Suco de cranberry",
      "5 gotas de suco de limão",
      "Cubos de gelo"
    ],
    "notes": [],
    "recipeInstructions": [
      "Coloque 3 pedras de gelo no copo e pingue algumas gotas de limão.",
      "Adicione o bacardi big apple.",
      "Mexa levemente e adicione o suco de cranberry à gosto.",
      "Se achar necessário, acrescente mais gelo."
    ],
    "image": "appleberry.jpg"
  },
  {
    "id": 9,
    "name": "B-52",
    "recipeCategory": "Alcoólico",
    "keywords": [
      "Forte",
      "Doce",
      "Cremoso"
    ],
    "serveIn": "Copo",
    "recipeCuisine": "",
    "recipeIngredient": [
      "½ dose de Bailey's",
      "½ dose de Grand Marnier",
      "½ dose de licor de café"
    ],
    "notes": [],
    "recipeInstructions": [
      "Adicione os ingredientes com o auxílio de uma colher bailarina nessa ordem:",
      "O licor de café.",
      "O Bailey's.",
      "O Grand Marnier.",
      "O drink ficará com 3 camadas.",
      "Ao servir, pode ser colocado fogo no topo."
    ],
    "image": "b_52.jpg"
  },
  {
    "id": 10,
    "name": "Bloody Mary",
    "recipeCategory": "Alcoólico",
    "keywords": [
      "Forte"
    ],
    "serveIn": "Copo",
    "recipeCuisine": "",
    "recipeIngredient": [
      "1 dose de vodka",
      "150 ml de suco de tomate",
      "1 colher (chá) de molho inglês",
      "1 colher (chá) de suco de limão",
      "4 gotas de Tabasco.",
      "½ colher (café) de sal",
      "Pimenta-do-Reino preta moída a gosto",
      "1 talo de salsão e/ou um pedaço de limão siciliano para decorar"
    ],
    "notes": [],
    "recipeInstructions": [
      "Comece colocando o molho inglês diretamente no copo.",
      "Adicione o suco de limão, o Tabasco e o sal.",
      "Misture bem e adicione o gelo.",
      "Acrescente a vodka e, por último, o suco de tomate.",
      "Tempere com a pimenta-do-reino preta moída a gosto.",
      "Misture levemente com uma colher e decore com a fatia de limão siciliano e/ou o talo de salsão."
    ],
    "image": "bloody_mary.jpg"
  },
  {
    "id": 11,
    "name": "Bourbon Rickey",
    "recipeCategory": "Alcoólico",
    "keywords": [
      "Refrescante"
    ],
    "serveIn": "Copo",
    "recipeCuisine": "",
    "recipeIngredient": [
      "1 limão",
      "1 dose de bourbon",
      "Club Soda",
      "Cubos de gelo"
    ],
    "notes": [],
    "recipeInstructions": [
      "Coloque o gelo picado no copo, esprema meio limão e jogue a casca dentro do copo.",
      "Adicione o bourbon e complete com a Club Soda.",
      "Mexa levemente para misturar, decore com uma fatia de limão e sirva."
    ],
    "image": "bourbon_rickey.jpg"
  },
  {
    "id": 12,
    "name": "Caipirinha",
    "recipeCategory": "Alcoólico",
    "keywords": [
      "Forte",
      "Doce"
    ],
    "serveIn": "Copo",
    "recipeCuisine": "Brasil",
    "recipeIngredient": [
      "1 dose de cachaça",
      "1 limão tahiti médio",
      "2 colheres (sopa) rasas de açúcar refinado",
      "Cubos de gelo"
    ],
    "notes": [],
    "recipeInstructions": [
      "Corte as pontas do limão tahiti e corte-o em 4, retirando o miolo branco dos gomos.",
      "Em uma coqueteleira use o pilão para macerar levemente o limão junto com o açúcar.",
      "Adicione o gelo e, em seguida, a cachaça.",
      "Agite bem e despeje tudo no copo, sem coar."
    ],
    "image": "caipirinha.jpg"
  },
  {
    "id": 13,
    "name": "Caipiroska de Ameixa",
    "recipeCategory": "Alcoólico",
    "keywords": [
      "Forte",
      "Doce"
    ],
    "serveIn": "Copo",
    "recipeCuisine": "Brasil",
    "recipeIngredient": [
      "1 dose de vodka",
      "1 ameixa grande",
      "1 colher (sopa) rasa de açúcar"
    ],
    "notes": [],
    "recipeInstructions": [
      "Corte a ameixa em pedaços pequenos, tirando o caroço.",
      "Em uma coqueteleira, macere a ameixa junto com o açúcar.",
      "Adicione o gelo e a dose de vodka.",
      "Agite levemente e despeje tudo no copo, sem coar."
    ],
    "image": "caipiroska_de_ameixa.jpg"
  },
  {
    "id": 14,
    "name": "Caipirinha de Tangerina com Pimenta Rosa",
    "recipeCategory": "Alcoólico",
    "keywords": [
      "Doce",
      "Refrescante"
    ],
    "serveIn": "Copo",
    "recipeCuisine": "Brasil",
    "recipeIngredient": [
      "2 doses de cachaça",
      "½ tangerina",
      "2 colheres (sobremesa) de açúcar",
      "1 colher (sobremesa) de pimenta rosa",
      "Cubos de gelo"
    ],
    "notes": [],
    "recipeInstructions": [
      "Corte a tangerina em fatias grossas e macere com o açúcar no fundo do copo.",
      "Coloque a pimenta rosa e a cachaça.",
      "Mexa levemente para misturar os ingredientes e adicione gelo até que alcance a borda do copo."
    ],
    "image": "caipirinha_de_tangerina_com_pimenta_rosa.jpg"
  },
  {
    "id": 15,
    "name": "Cape Cod",
    "recipeCategory": "Alcoólico",
    "keywords": [
      "Refrescante"
    ],
    "serveIn": "Copo",
    "recipeCuisine": "",
    "recipeIngredient": [
      "1 dose de vodka",
      "2 ½ doses de suco de cranberry",
      "Cubos de gelo",
      "1 fatia triangular de limão"
    ],
    "notes": [],
    "recipeInstructions": [
      "Encha o copo com gelo.",
      "Adicione a vodka e acrescente o suco de cranberry.",
      "Mexa bem, decore com a fatia de limão e sirva."
    ],
    "image": "cape_cod.jpg"
  },
  {
    "id": 16,
    "name": "Choconhaque",
    "recipeCategory": "Alcoólico",
    "keywords": [
      "Doce",
      "Amargo",
      "Cremoso"
    ],
    "serveIn": "Copo",
    "recipeCuisine": "",
    "recipeIngredient": [
      "1 litro de leite integral",
      "½ lata de leite condensado",
      "1 colher (sobremesa) de essência de baunilha",
      "2 colheres (sopa) rasas de amido de milho",
      "200 gramas de chocolate meio amargo",
      "3 doses de conhaque"
    ],
    "notes": [],
    "recipeInstructions": [
      "Pique o chocolate.",
      "Numa panela funda, coloque todos os ingredientes, menos o conhaque.",
      "Ferva por aproximadamente 10 minutos em fogo médio, ou até que o caldo fique levemente grosso.",
      "Desligue o fogo, acrescente o conhaque e misture bem.",
      "Sirva quente."
    ],
    "image": "choconhaque.jpg"
  },
  {
    "id": 17,
    "name": "Clericot (Sangria Blanche)",
    "recipeCategory": "Alcoólico",
    "keywords": [
      "Refrescante"
    ],
    "serveIn": "Taça",
    "recipeCuisine": "",
    "recipeIngredient": [
      "750 ml de vinho branco",
      "1 dose de Cointreau",
      "1 lata de Club Soda ou água com gás",
      "1 limão",
      "1 laranja",
      "6 morangos",
      "1 pêssego",
      "Hortelã",
      "De 4 a 8 colheres (sopa) rasas de açúcar",
      "Cubos de gelo"
    ],
    "notes": [],
    "recipeInstructions": [
      "Corte a laranja e o limão em rodelas.",
      "Corte os morangos e o pêssego em pedaços.",
      "Coloque as frutas numa poncheira ou numa jarra e encha até a metade de gelo.",
      "Adicione o Cointreau, o vinho branco e, por fim, o Club Soda ou a água com gás.",
      "Misture levemente com a ajuda de uma colher bailarina.",
      "Decore com um ramo de hortelã.",
      "Ao servir, derrame apenas o líquido na taça."
    ],
    "image": "clericot_sangria_blanche.jpg"
  },
  {
    "id": 18,
    "name": "Coquetel de Melancia",
    "recipeCategory": "Alcoólico",
    "keywords": [
      "Doce",
      "Refrescante"
    ],
    "serveIn": "Copo",
    "recipeCuisine": "",
    "recipeIngredient": [
      "50 gramas de melancia",
      "50 ml de saquê",
      "2 colheres (sopa) de açúcar",
      "20 ml de suco de limão",
      "Cubos de gelo"
    ],
    "notes": [],
    "recipeInstructions": [
      "Em um coqueteleira, coloque a melancia, o açúcar, o suco de limão e alguns cubos de gelo.",
      "Agite bem.",
      "Despeje toda a mistura no copo e acrescente o saquê.",
      "Misture com um mexedor.",
      "Decore com um raminho de hortelã."
    ],
    "image": "coquetel_de_melancia.jpg"
  },
  {
    "id": 19,
    "name": "Coquetel de Natal",
    "recipeCategory": "Alcoólico",
    "keywords": [
      "Cremoso"
    ],
    "serveIn": "Taça De Coquetel",
    "recipeCuisine": "",
    "recipeIngredient": [
      "1 lata de leite condensado",
      "A mesma medida de vinho do porto",
      "2 doses de conhaque",
      "5 nozes picadas",
      "10 pedras de gelo picadas"
    ],
    "notes": [],
    "recipeInstructions": [
      "No liquidificador, bata o leite condensado, o vinho do porto, o conhaque e as nozes.",
      "Acrescente o gelo e bata novamente até obter uma mistura homogênea.",
      "Sirva na taça e adicione nozes moídas por cima da bebida."
    ],
    "image": "coquetel_de_natal.jpg"
  },
  {
    "id": 20,
    "name": "Cosmopolitan",
    "recipeCategory": "Alcoólico",
    "keywords": [
      "Clássico",
      "Forte"
    ],
    "serveIn": "Taça De Coquetel",
    "recipeCuisine": "Estados Unidos",
    "recipeIngredient": [
      "1 dose de vodka",
      "2 doses de suco de cranberry",
      "½ dose de Cointreau",
      "¼ dose de suco de limão",
      "Cubos de gelo",
      "Zeste de laranja para decorar"
    ],
    "notes": [],
    "recipeInstructions": [
      "Coloque gelo até a metade da coqueteleira.",
      "Adicione a vodka, o Cointreau, o suco de limão e, por fim, o suco de cranberry.",
      "Agite bem e transfira a bebida, sem o gelo, para a taça.",
      "Torça a zeste de laranja e coloque na borda da taça para decorar."
    ],
    "image": "cosmopolitan.jpg"
  },
  {
    "id": 21,
    "name": "Death in the Afternoon",
    "recipeCategory": "Alcoólico",
    "keywords": [
      "Forte",
      "Refrescante",
      "Gelado"
    ],
    "serveIn": "Taça",
    "recipeCuisine": "",
    "recipeIngredient": [
      "1 ½ dose de absinto",
      "4 ½ doses de espumante gelado"
    ],
    "notes": [],
    "recipeInstructions": [
      "Coloque o absinto na taça e complete com o espumante.",
      "Sirva gelado."
    ],
    "image": "death_in_the_afternoon.jpg"
  },
  {
    "id": 22,
    "name": "Dorchester",
    "recipeCategory": "Alcoólico",
    "keywords": [
      "Clássico",
      "Doce"
    ],
    "serveIn": "Taça",
    "recipeCuisine": "",
    "recipeIngredient": [
      "1 ½ doses de gin",
      "½ dose de licor maraschino",
      "½ dose de xarope simples",
      "½ dose de suco de toranja",
      "¾ dose de suco de limão",
      "Cubos de gelo à vontade"
    ],
    "notes": [],
    "recipeInstructions": [
      "Coloque gelo até a metade da coqueteleira",
      "Acrescente os ingredientes, começando pelos destilados e terminando pelos cítricos.",
      "Agite bem e coe pelo strainer, despejando apenas o líquido na taça."
    ],
    "image": "dorchester.jpg"
  },
  {
    "id": 23,
    "name": "Felix Khoury",
    "recipeCategory": "Alcoólico",
    "keywords": [
      "Forte",
      "Seco",
      "Refrescante"
    ],
    "serveIn": "Taça",
    "recipeCuisine": "Brasil",
    "recipeIngredient": [
      "100 ml de vodka",
      "20 ml vermute seco",
      "30 ml Curaçao Blue",
      "1 fatia de carambola para decorar",
      "Cubos de gelo"
    ],
    "notes": [],
    "recipeInstructions": [
      "Encha a coqueteleira com gelo.",
      "Adicione a vodka, o vermute seco e o Curaçao Blue.",
      "Agite bem e despeje apenas o líquido na taça, passando pelo strainer e por uma peneira com gelo dentro.",
      "Decore com uma fatia de carambola."
    ],
    "image": "felix_khoury.jpg"
  },
  {
    "id": 24,
    "name": "Eggnog",
    "recipeCategory": "Alcoólico",
    "keywords": [
      "Doce",
      "Cremoso",
      "Gelado"
    ],
    "serveIn": "Copo",
    "recipeCuisine": "Inglaterra",
    "recipeIngredient": [
      "1 gema",
      "1 clara",
      "12 g de açúcar",
      "100 ml de leite integral",
      "½ dose (25ml) de rum",
      "½ dose (25ml) de conhaque",
      "1 colher (chá) de essência de baunilha",
      "¼ colher (chá) de sal",
      "40 ml de creme de leite batido",
      "Noz-moscada a gosto"
    ],
    "notes": [],
    "recipeInstructions": [
      "Bata a gema num bowl.",
      "Aos poucos, vá juntando metade do açúcar, batendo até ficar com uma cor esbranquiçada.",
      "Acrescente o rum, o conhaque, a essência de baunilha e o sal.",
      "Misture bem e deixe na geladeira até estar bem gelado.",
      "No copo, bata o creme de leite.",
      "Em outro copo bata muito bem a clara até ficar firme e vá juntando o resto do açúcar aos poucos.",
      "Despeje a mistura anterior (das gemas) e o creme de leite no copo da clara.",
      "Acrescente a noz-moscada e mexa até ficar tudo bem misturado.",
      "Sirva bem gelado."
    ],
    "image": "eggnog.jpg"
  },
  {
    "id": 25,
    "name": "Energy Drink",
    "recipeCategory": "Alcoólico",
    "keywords": [
      "Seco",
      "Refrescante"
    ],
    "serveIn": "Taça",
    "recipeCuisine": "",
    "recipeIngredient": [
      "1 dose de vinho branco seco",
      "Frutas variadas picadas",
      "200 ml de energético",
      "Cubos de gelo"
    ],
    "notes": [],
    "recipeInstructions": [
      "Na coqueteleira, misture o vinho branco seco com o energético.",
      "Acrescente algumas pedras de gelo e agite brevemente.",
      "Despeje na taça e acrescente as frutas."
    ],
    "image": "energy_drink.jpg"
  },
  {
    "id": 26,
    "name": "Floresta Negra",
    "recipeCategory": "Alcoólico",
    "keywords": [
      "Doce",
      "Cremoso"
    ],
    "serveIn": "Copo",
    "recipeCuisine": "",
    "recipeIngredient": [
      "½ dose de licor de cacau",
      "½ dose de licor de cereja",
      "25 ml de chantilly",
      "Cubos de gelo",
      "1 cereja marrasquino",
      "hortelã"
    ],
    "notes": [],
    "recipeInstructions": [
      "Coloque algumas pedras de gelo na coqueteleira.",
      "Adicione o licor de cacau, o licor de cereja e o chantilly.",
      "Despeje no copo passando pelo strainer, retendo o gelo.",
      "Decore com uma cereja marrasquino e um raminho de hortelã."
    ],
    "image": "floresta_negra.jpg"
  },
  {
    "id": 27,
    "name": "French Connection",
    "recipeCategory": "Alcoólico",
    "keywords": [
      "Forte",
      "Doce"
    ],
    "serveIn": "Copo",
    "recipeCuisine": "",
    "recipeIngredient": [
      "½ dose de conhaque",
      "½ dose de Amaretto",
      "Cubos de gelo"
    ],
    "notes": [],
    "recipeInstructions": [
      "Coloque gelo na coqueteleira.",
      "Acrescente o conhaque.",
      "Adicione o Amaretto.",
      "Mexa levemente com uma colher bailarina para combinar os ingredientes.",
      "Despeje com o gelo no copo e sirva."
    ],
    "image": "french_connection.jpg"
  },
  {
    "id": 28,
    "name": "Gimlet",
    "recipeCategory": "Alcoólico",
    "keywords": [
      "Forte"
    ],
    "serveIn": "Taça De Coquetel",
    "recipeCuisine": "Estados Unidos",
    "recipeIngredient": [
      "2 ½ doses de gin",
      "½ dose de suco de limão",
      "½ dose de xarope simples",
      "Casca de limão",
      "Cubos de gelo"
    ],
    "notes": [],
    "recipeInstructions": [
      "Encha a coqueteleira com gelo.",
      "Adicione o gin, o suco de limão e o xarope simples.",
      "Agite bem e coe pelo strainer, despejando apenas o líquido na taça.",
      "Decore com a casca de limão e sirva."
    ],
    "image": "gimlet.jpg"
  },
  {
    "id": 29,
    "name": "Gin Cosmo",
    "recipeCategory": "Alcoólico",
    "keywords": [
      "Forte",
      "Seco",
      "Gelado"
    ],
    "serveIn": "Taça De Coquetel",
    "recipeCuisine": "",
    "recipeIngredient": [
      "2 doses de gin",
      "½ dose de Cointreau",
      "3 doses de suco de cranberry",
      "1 colher de sopa de suco de limão",
      "Cubos de gelo"
    ],
    "notes": [],
    "recipeInstructions": [
      "Coloque gelo até a metade da coqueteleira.",
      "Adicione o gin, o Cointreau e o suco de cranberry e agite bem.",
      "Coe pelo strainer, despejando apenas o líquido na taça.",
      "Misture o suco de limão e decore com uma zeste de limão.",
      "Sirva gelado."
    ],
    "image": "gin_cosmo.jpg"
  },
  {
    "id": 30,
    "name": "Gin Tônica",
    "recipeCategory": "Alcoólico",
    "keywords": [
      "Refrescante"
    ],
    "serveIn": "Taça",
    "recipeCuisine": "Inglaterra",
    "recipeIngredient": [
      "1 dose de gin",
      "Água tônica",
      "1 limão Tahiti",
      "Cubos de gelo"
    ],
    "notes": [],
    "recipeInstructions": [
      "Coloque o gelo na taça.",
      "Esprema algumas gotas do limão por cima do gelo.",
      "Coloque uma rodela de limão e adicione o gin.",
      "Complete com a água tônica e sirva."
    ],
    "image": "gin_tônica.jpg"
  },
  {
    "id": 31,
    "name": "Grant's Twist",
    "recipeCategory": "Alcoólico",
    "keywords": [
      "Refrescante"
    ],
    "serveIn": "Copo",
    "recipeCuisine": "",
    "recipeIngredient": [
      "1 dose de uísque",
      "3 gotas de suco de framboesa",
      "Limonada a gosto.",
      "2 rodelas de limão para decorar"
    ],
    "notes": [],
    "recipeInstructions": [
      "Encha o copo com pedras de gelo.",
      "Adicione o uísque e, em seguida, o suco de framboesa, misturando levemente com uma colher bailarina.",
      "Complete o copo com limonada e decore com duas rodelas de limão."
    ],
    "image": "grants_twist.jpg"
  },
  {
    "id": 32,
    "name": "Horse's Neck",
    "recipeCategory": "Alcoólico",
    "keywords": [
      "Refrescante"
    ],
    "serveIn": "Copo",
    "recipeCuisine": "",
    "recipeIngredient": [
      "1 dose de conhaque",
      "3 doses de Ginger Ale ou espumante",
      "1 gota de angostura",
      "Cubos de gelo",
      "Limão"
    ],
    "notes": [],
    "recipeInstructions": [
      "Coloque algumas pedras de gelo no copo.",
      "Despeje o conhaque e o Ginger Ale (ou espumante) por cima do gelo.",
      "Mexa delicadamente com uma colher bailarina e decore com raspas de limão.",
      "Pingue algumas gotas de angostura e sirva."
    ],
    "image": "horses_neck.jpg"
  },
  {
    "id": 33,
    "name": "Jamaican Breeze",
    "recipeCategory": "Alcoólico",
    "keywords": [
      "Refrescante"
    ],
    "serveIn": "Copo",
    "recipeCuisine": "Jamaica",
    "recipeIngredient": [
      "1 fatia de gengibre fresco",
      "1½ dose de rum ouro",
      "2 doses de suco de abacaxi",
      "½ dose de xarope simples",
      "Angostura",
      "Cubos de gelo",
      "Uma fatia de limão"
    ],
    "notes": [],
    "recipeInstructions": [
      "Na coqueteleira, macere o gengibre fresco e adicione o rum.",
      "Acrescente então o suco de abacaxi e o xarope simples.",
      "Complete com gelo e agite bem.",
      "Coe com o strainer, servindo somente o líquido no copo.",
      "Adicione gelo e decore com a fatia de limão.",
      "Pingue umas gotas de angostura por cima e sirva."
    ],
    "image": "jamaican_breeze.jpg"
  },
  {
    "id": 34,
    "name": "Kamikaze",
    "recipeCategory": "Alcoólico",
    "keywords": [
      "Forte"
    ],
    "serveIn": "Taça De Coquetel",
    "recipeCuisine": "",
    "recipeIngredient": [
      "½ dose de vodka",
      "½ dose de Cointreau",
      "½ dose de suco de limão fresco",
      "Gelo picado"
    ],
    "notes": [],
    "recipeInstructions": [
      "Encha a coqueteleira com o gelo picado.",
      "Adicione a vodka e o Cointreau e agite brevemente.",
      "Coe através do strainer, despejando apenas o conteúdo na taça.",
      "Decore com uma fatia de limão."
    ],
    "image": "kamikaze.jpg"
  },
  {
    "id": 35,
    "name": "Kir Royal",
    "recipeCategory": "Alcoólico",
    "keywords": [],
    "serveIn": "Taça",
    "recipeCuisine": "França",
    "recipeIngredient": [
      "1 dose de licor de cassis",
      "Espumante branco",
      "1 cereja marrasquino"
    ],
    "notes": [],
    "recipeInstructions": [
      "Coloque o licor de cassis na taça e complete com o espumante.",
      "Decore com uma cereja marrasquino."
    ],
    "image": "kir_royal.jpg"
  },
  {
    "id": 36,
    "name": "Lagerita",
    "recipeCategory": "Alcoólico",
    "keywords": [
      "Refrescante"
    ],
    "serveIn": "Copo",
    "recipeCuisine": "México",
    "recipeIngredient": [
      "Sal",
      "2 doses de tequila",
      "¾ dose de Cointreau",
      "1 dose de suco de limão",
      "1 lata de cerveja tipo lager",
      "Cubos de gelo",
      "1 fatia de limão"
    ],
    "notes": [],
    "recipeInstructions": [
      "Molhe a borda do copo e o coloque de cabeça para baixo num prato com sal.",
      "Na coqueteleira coloque a tequila, o Cointreau e o suco de limão, acrescente o gelo e agite bem.",
      "Coloque uns cubos de gelo no copo e despeje a mistura, coando pelo strainer.",
      "Complete com a cerveja.",
      "Decore com uma rodela de limão."
    ],
    "image": "lagerita.jpg"
  },
  {
    "id": 37,
    "name": "Levanta Defunto",
    "recipeCategory": "Alcoólico",
    "keywords": [
      "Forte"
    ],
    "serveIn": "Taça De Coquetel",
    "recipeCuisine": "",
    "recipeIngredient": [
      "1 dose de conhaque",
      "1 dose de Fernet Branca",
      "1 dose de licor de menta",
      "Cubos de gelo"
    ],
    "notes": [],
    "recipeInstructions": [
      "Encha a coqueteleira com gelo.",
      "Adicione o conhaque, o Fernet Branca e o licor de menta.",
      "Agite bem e coe pelo strainer, despejando apenas o líquido na taça."
    ],
    "image": "levanta_defunto.jpg"
  },
  {
    "id": 38,
    "name": "Levanta Defunto #1",
    "recipeCategory": "Alcoólico",
    "keywords": [
      "Forte",
      "Doce"
    ],
    "serveIn": "Taça De Coquetel",
    "recipeCuisine": "França",
    "recipeIngredient": [
      "2 doses de conhaque",
      "1 dose de conhaque de maçã",
      "1 dose de vermute doce",
      "Cubos de gelo"
    ],
    "notes": [],
    "recipeInstructions": [
      "Encha a coqueteleira com gelo.",
      "Adicione o conhaque, o conhaque de maçã e o vermute doce.",
      "Agite bem e coe pelo strainer, despejando apenas o líquido na taça."
    ],
    "image": "levanta_defunto_1.jpg"
  },
  {
    "id": 39,
    "name": "Levanta Defunto #2",
    "recipeCategory": "Alcoólico",
    "keywords": [
      "Forte"
    ],
    "serveIn": "Taça De Coquetel",
    "recipeCuisine": "",
    "recipeIngredient": [
      "½ dose de gin",
      "½ dose de Cointreau",
      "½ dose de Lillet Blanc",
      "½ dose de suco de limão",
      "1 pitada de absinto",
      "Cubos de gelo",
      "1 cereja marrasquino"
    ],
    "notes": [],
    "recipeInstructions": [
      "Encha a coqueteleira com gelo.",
      "Adicione o gin, o Cointreau e o Lillet Blanc.",
      "Acrescente o suco de limão e a pitada de absinto.",
      "Agite bem e coe pelo strainer, despejando apenas o líquido na taça.",
      "Coloque a cereja marrasquino e sirva."
    ],
    "image": "levanta_defunto_2.jpg"
  },
  {
    "id": 40,
    "name": "Limão e Gengibre",
    "recipeCategory": "",
    "keywords": [
      "Refrescante"
    ],
    "serveIn": "Taça De Coquetel",
    "recipeCuisine": "",
    "recipeIngredient": [
      "Suco de 2 limões frescos",
      "1 colher (chá) de gengibre ralado",
      "12 gotas de adoçante",
      "500 ml de água com gás"
    ],
    "notes": [],
    "recipeInstructions": [
      "Numa jarra, esprema os limões e coloque o gengibre ralado.",
      "Acrescente o adoçante e a água com gás.",
      "Mexa delicadamente com a colher bailarina para misturar.",
      "Coloque gelo nas taças e despeje o conteúdo.",
      "Decore com fatias de limão e sirva."
    ],
    "image": "limão_e_gengibre.jpg"
  },
  {
    "id": 41,
    "name": "Lolita go Home",
    "recipeCategory": "Alcoólico",
    "keywords": [
      "Seco",
      "Doce",
      "Refrescante"
    ],
    "serveIn": "Copo",
    "recipeCuisine": "",
    "recipeIngredient": [
      "1 dose de uísque",
      "1 dose de vinho branco seco",
      "½ dose de xarope simples",
      "2 doses de suco de toranja",
      "Gelo a vontade"
    ],
    "notes": [],
    "recipeInstructions": [
      "Coloque o gelo na coqueteleira.",
      "Adicione o uísque e o vinho branco.",
      "Acrescente o xarope simples e o suco de toranja.",
      "Agite bem, despeje no copo e decore com espirais de casca de toranja."
    ],
    "image": "lolita_go_home.jpg"
  },
  {
    "id": 42,
    "name": "Lucid Frappe",
    "recipeCategory": "Alcoólico",
    "keywords": [
      "Refrescante"
    ],
    "serveIn": "Taça",
    "recipeCuisine": "",
    "recipeIngredient": [
      "1 dose de absinto",
      "½ dose de xarope simples",
      "6 a 8 folhas de hortelã",
      "Club Soda",
      "Cubos de gelo"
    ],
    "notes": [],
    "recipeInstructions": [
      "Coloque as folhas de hortelã na coqueteleira.",
      "Acrescente o absinto e o xarope simples.",
      "Adicione um pouco de gelo picado e agite bem.",
      "Despeje na taça e complete com a Club Soda.",
      "Decore com um raminho de hortelã."
    ],
    "image": "lucid_frappe.jpg"
  },
  {
    "id": 43,
    "name": "Manhattan",
    "recipeCategory": "Alcoólico",
    "keywords": [
      "Clássico",
      "Forte"
    ],
    "serveIn": "Taça De Coquetel",
    "recipeCuisine": "Estados Unidos",
    "recipeIngredient": [
      "1 dose de uísque",
      "1 dose de Vermute Vermelho",
      "Angostura",
      "1 cereja marrasquino"
    ],
    "notes": [],
    "recipeInstructions": [
      "Na taça já gelada, coloque o uísque.",
      "Adicione o vermute vermelho e mexa levemente.",
      "Pingue algumas gotas de Angostura e coloque a cereja marrasquino dentro."
    ],
    "image": "manhattan.jpg"
  },
  {
    "id": 44,
    "name": "Margarita",
    "recipeCategory": "Alcoólico",
    "keywords": [
      "Clássico",
      "Refrescante"
    ],
    "serveIn": "Taça",
    "recipeCuisine": "México",
    "recipeIngredient": [
      "1 dose de tequila",
      "½ dose de Cointreau",
      "½ dose de suco de limão",
      "2 colheres (chá) bem cheias de açúcar refinado",
      "Cubos de gelo",
      "1 lasca de limão",
      "sal"
    ],
    "notes": [],
    "recipeInstructions": [
      "Espalhe o sal sobre um prato.",
      "Esfregue a lasca de limão em meia borda da taça.",
      "Mergulhe a borda da taça no sal e reserve.",
      "Na coqueteleira, coloque o suco de limão com o açúcar e agite até dissolver parcialmente (cerca de 5 segundos).",
      "Adicione o Cointreau, a tequila e 1 xícara de cubos de gelo.",
      "Agite vigorosamente durante 25 segundos e despeje tudo na taça que estava reservada.",
      "Coloque mais alguns cubos de gelo na taça, decore com uma rodela de limão e sirva."
    ],
    "image": "margarita.jpg"
  },
  {
    "id": 45,
    "name": "Martini de Melancia",
    "recipeCategory": "Alcoólico",
    "keywords": [
      "Doce",
      "Refrescante"
    ],
    "serveIn": "Taça De Coquetel",
    "recipeCuisine": "",
    "recipeIngredient": [
      "4 doses de suco de melancia",
      "2 doses de vodka",
      "1 dose de xarope simples",
      "Suco de 1 limão",
      "Cubos de gelo",
      "Fatias de melancia"
    ],
    "notes": [],
    "recipeInstructions": [
      "Encha a coqueteleira com gelo.",
      "Adicione todos os ingredientes e agite bem.",
      "Coe, despejando apenas o líquido na taça.",
      "Decore com uma fatia de melancia."
    ],
    "image": "martini_de_melancia.jpg"
  },
  {
    "id": 46,
    "name": "Martini Wasabi",
    "recipeCategory": "Alcoólico",
    "keywords": [
      "Forte",
      "Seco",
      "Gelado"
    ],
    "serveIn": "Taça De Coquetel",
    "recipeCuisine": "",
    "recipeIngredient": [
      "50 ml de vodka",
      "20 ml de vermute seco",
      "1 colher (café) de wasabi",
      "20 ml de licor de lichia",
      "Cubos de gelo"
    ],
    "notes": [],
    "recipeInstructions": [
      "Coloque gelo até a metade da coqueteleira.",
      "Adicione a vodka e o vermute seco.",
      "Acrescente o wasabi, finalizando com o licor de lichia.",
      "Agite bem e coe pelo strainer, despejando apenas o líquido na taça.",
      "Sirva bem gelado."
    ],
    "image": "martini_wasabi.jpg"
  },
  {
    "id": 47,
    "name": "Michelada",
    "recipeCategory": "Alcoólico",
    "keywords": [
      "Refrescante"
    ],
    "serveIn": "Copo",
    "recipeCuisine": "México",
    "recipeIngredient": [
      "1 lata de cerveja (pilsen ou lager)",
      "2 colheres de sopa de sal",
      "1 colher (sopa) de chilli em pó",
      "2 colheres (sopa) de suco de limão",
      "1 limão",
      "Tabasco",
      "molho inglês",
      "Cubos de gelo"
    ],
    "notes": [],
    "recipeInstructions": [
      "Misture o sal e o chilli em pó em um prato.",
      "Passe um pedaço de limão na borda do copo e vire-o contra o prato para preencher suas bordas.",
      "No copo, pingue algumas gotas de molho inglês e algumas gotas de Tabasco.",
      "Adicione cubos de gelo até metade do copo.",
      "Acrescente o suco de limão e complete com a cerveja.",
      "Decore com um pedaço de limão."
    ],
    "image": "michelada.jpg"
  },
  {
    "id": 48,
    "name": "Mojito",
    "recipeCategory": "Alcoólico",
    "keywords": [
      "Clássico",
      "Refrescante"
    ],
    "serveIn": "Copo",
    "recipeCuisine": "Cuba",
    "recipeIngredient": [
      "1 dose de rum",
      "10 folhas frescas de hortelã",
      "1 limão pequeno",
      "2 colheres (sopa) de açúcar refinado",
      "½ xícara de água com gás",
      "5 ou 6 cubos de gelo"
    ],
    "notes": [],
    "recipeInstructions": [
      "Corte o limão em quatro gomos.",
      "Coloque as folhas de hortelã e 1 gomo de limão no copo.",
      "Macere suavemente com um pilão a hortelã e o limão para liberar o óleo da hortelã e o suco do limão.",
      "Adicione mais 2 gomos do limão e o açúcar.",
      "Pressione o pilão sobre o limão para tirar o seu suco.",
      "Encha o copo quase até a boca com gelo.",
      "Despeje o rum sobre o gelo e complete com a água com gás.",
      "Mexa com uma colher bailarina, prove e, se necessário, coloque mais açúcar.",
      "Decore com o gomo restante do limão e um ramo de hortelã.",
      "Sirva com canudo."
    ],
    "image": "mojito.jpg"
  },
  {
    "id": 49,
    "name": "Moscow Mule (brasileiro)",
    "recipeCategory": "Alcoólico",
    "keywords": [
      "Clássico",
      "Refrescante"
    ],
    "serveIn": "Copo",
    "recipeCuisine": "Estados Unidos",
    "recipeIngredient": [
      "Gengibre",
      "1 clara de ovo",
      "½ dose de suco de limão",
      "½ dose de xarope simples"
    ],
    "notes": [],
    "recipeInstructions": [
      "Rale cerca de 2 cm de gengibre e esprema para tirar seu suco, cerca de ½ dose.",
      "Coloque num bowl a clara de ovo junto com o xarope simples.",
      "Adicione o suco do gengibre e o suco de limão.",
      "Bata bem com um fuê até que vire uma espuma. reserve na geladeira."
    ],
    "image": "moscow_mule_brasileiro.jpg"
  },
  {
    "id": 50,
    "name": "Negroni",
    "recipeCategory": "Alcoólico",
    "keywords": [
      "Clássico",
      "Forte",
      "Doce",
      "Amargo"
    ],
    "serveIn": "Copo",
    "recipeCuisine": "Itália",
    "recipeIngredient": [
      "1 dose de Campari",
      "1 dose de gin",
      "1 dose de vermute doce",
      "1 casca de laranja",
      "Cubos de gelo"
    ],
    "notes": [],
    "recipeInstructions": [
      "Encha o copo com gelo até a borda.",
      "Adicione o campari, o gin e o vermute doce.",
      "Mexa levemente para misturar até que fique com a cor vermelho vivo.",
      "Opcionalmente, você pode colocar um pedaço de casca de laranja dentro do copo, mexendo levemente para soltar o sabor."
    ],
    "image": "negroni.jpg"
  },
  {
    "id": 51,
    "name": "Paradise",
    "recipeCategory": "Alcoólico",
    "keywords": [],
    "serveIn": "Taça De Coquetel",
    "recipeCuisine": "",
    "recipeIngredient": [],
    "notes": [],
    "recipeInstructions": [
      "Coloque as frutas em uma coqueteleira e macere com o pilão até que fiquem em polpa, sem pedaços grandes.",
      "Adicione a vodka e o xarope simples e agite novamente.",
      "Despeje na taça e complete com gelo.",
      "Decore com uma fatia de kiwi com casca."
    ],
    "image": "paradise.jpg"
  },
  {
    "id": 52,
    "name": "Orgasm",
    "recipeCategory": "Alcoólico",
    "keywords": [
      "Forte",
      "Cremoso"
    ],
    "serveIn": "Copo",
    "recipeCuisine": "",
    "recipeIngredient": [
      "½ dose de Cointreau",
      "½ dose de Bailey's",
      "¼ dose de Grand Marnier",
      "Cubos de gelo"
    ],
    "notes": [],
    "recipeInstructions": [
      "Coloque alguns cubos de gelo no copo.",
      "Adicione o Cointreau, o Bailey's e o Grand Marnier.",
      "Mexa levemente com uma colher bailarina e decore com uma cereja marrasquino."
    ],
    "image": "orgasm.jpg"
  },
  {
    "id": 53,
    "name": "Piña Colada",
    "recipeCategory": "Alcoólico",
    "keywords": [
      "Refrescante",
      "Cremoso"
    ],
    "serveIn": "Taça",
    "recipeCuisine": "",
    "recipeIngredient": [
      "1 dose de rum",
      "1 ½ dose de suco de abacaxi",
      "½ dose de leite de coco",
      "1 dose de leite condensado",
      "½ dose de creme de leite",
      "Cubos de gelo"
    ],
    "notes": [],
    "recipeInstructions": [
      "Coloque gelo até a metade da coqueteleira, adicione o rum e o suco de abacaxi.",
      "Mexa levemente e acrescente o leite de coco, o leite condensado e o creme de leite.",
      "Agite bem e coe pelo strainer, despejando apenas o líquido na taça."
    ],
    "image": "piña_colada.jpg"
  },
  {
    "id": 54,
    "name": "Pisco Sour",
    "recipeCategory": "Alcoólico",
    "keywords": [
      "Clássico",
      "Refrescante"
    ],
    "serveIn": "Taça",
    "recipeCuisine": "Peru",
    "recipeIngredient": [
      "1 dose de pisco",
      "½ dose de xarope simples",
      "½ dose de suco de limão",
      "½ clara de ovo",
      "Angostura",
      "Cubos de gelo"
    ],
    "notes": [],
    "recipeInstructions": [
      "Na coqueteleira, coloque o pisco, o xarope simples e o suco de limão.",
      "Acrescente a clara de ovo e agite bem por cerca de 10 segundos.",
      "Adicione gelo até a metade da coqueteleira e agite novamente, dessa vez por 20 segundos.",
      "Coe pelo strainer, despejando apenas o líquido na taça ou copo.",
      "Pingue algumas gotas de angostura e sirva."
    ],
    "image": "pisco_sour.jpg"
  },
  {
    "id": 55,
    "name": "Quentão de Cachaça",
    "recipeCategory": "Alcoólico",
    "keywords": [
      "Doce"
    ],
    "serveIn": "Copo",
    "recipeCuisine": "Brasil",
    "recipeIngredient": [
      "1 garrafa (600 ml) de cachaça",
      "600 ml de água filtrada",
      "500 g de açúcar refinado",
      "100 g de gengibre",
      "2 palitos de canela em pau",
      "8 cravos da índia",
      "Casca de uma laranja"
    ],
    "notes": [],
    "recipeInstructions": [
      "Limpe o gengibre e corte em pedaços de cerca de 1 cm cada.",
      "Numa panela grande, coloque o açúcar e o gengibre e aqueça em fogo médio até virar caramelo.",
      "Acrescente o cravo, a canela e a casca de laranja e cozinhe por 5 minutos.",
      "Adicione a água e ferva por meia hora, mexendo com uma colher de madeira no começo para dissolver o caramelo.",
      "Coloque a cachaça e ferva por mais 10 minutos.",
      "Sirva bem quente."
    ],
    "image": "quentão_de_cachaça.jpg"
  },
  {
    "id": 56,
    "name": "Rob Roy",
    "recipeCategory": "Alcoólico",
    "keywords": [
      "Clássico",
      "Forte",
      "Seco",
      "Doce"
    ],
    "serveIn": "Taça De Coquetel",
    "recipeCuisine": "",
    "recipeIngredient": [
      "½ dose de uísque",
      "15 ml de vermute doce",
      "Angostura",
      "Cubos de gelo"
    ],
    "notes": [],
    "recipeInstructions": [
      "Coloque gelo até a metade da coqueteleira.",
      "Adicione o uísque, o vermute doce e duas gotas de angostura.",
      "Agite bem e coe pelo strainer despejando apenas o líquido na taça ou no copo.",
      "Decore com uma fatia de limão"
    ],
    "image": "rob_roy.jpg"
  },
  {
    "id": 57,
    "name": "Sex On The Beach",
    "recipeCategory": "Alcoólico",
    "keywords": [
      "Clássico",
      "Doce"
    ],
    "serveIn": "Taça",
    "recipeCuisine": "Estados Unidos",
    "recipeIngredient": [
      "1 dose de vodka gelada",
      "½ dose de licor de pêssego",
      "suco de laranja",
      "xarope de groselha",
      "2 cubos de gelo moídos."
    ],
    "notes": [],
    "recipeInstructions": [
      "Coloque o gelo moído no copo ou na taça.",
      "Na coqueteleira, coloque a vodka, em seguida adicione o licor de pêssego e complete com o suco de laranja.",
      "Agite bem e despeje no copo ou na taça.",
      "Pingue algumas gotas de xarope de groselha para decorar."
    ],
    "image": "sex_on_the_beach.jpg"
  },
  {
    "id": 58,
    "name": "Sgroppino",
    "recipeCategory": "Alcoólico",
    "keywords": [
      "Refrescante",
      "Gelado"
    ],
    "serveIn": "Taça",
    "recipeCuisine": "Itália",
    "recipeIngredient": [
      "½ dose de vodka",
      "Prosecco gelado",
      "1 bola de sorvete de limão",
      "5 folhas de hortelã picadas"
    ],
    "notes": [],
    "recipeInstructions": [
      "Coloque a vodka na taça e complete com o prosecco.",
      "Adicione o sorvete de limão, sem mexer.",
      "Polvilhe a hortelã picada por cima e sirva imediatamente."
    ],
    "image": "sgroppino.jpg"
  },
  {
    "id": 59,
    "name": "Sidecar",
    "recipeCategory": "Alcoólico",
    "keywords": [
      "Clássico",
      "Refrescante"
    ],
    "serveIn": "Taça De Coquetel",
    "recipeCuisine": "",
    "recipeIngredient": [
      "1 dose conhaque",
      "10 ml de Cointreau",
      "10 ml de suco de limão",
      "Gelo picado"
    ],
    "notes": [],
    "recipeInstructions": [
      "Coloque um pouco de gelo picado na coqueteleira.",
      "Acrescente o conhaque, o Cointreau e o suco de limão.",
      "Agite bem e coe com o strainer, despejando somente o líquido na taça.",
      "Decore com uma fatia de limão."
    ],
    "image": "sidecar.jpg"
  },
  {
    "id": 60,
    "name": "Silent Siren",
    "recipeCategory": "Alcoólico",
    "keywords": [],
    "serveIn": "Taça",
    "recipeCuisine": "",
    "recipeIngredient": [
      "1 dose de gin",
      "1 dose de bénédictine",
      "1 dose de amaretto",
      "1 dose de suco de romã",
      "Laranja",
      "Angostura",
      "Cubos de gelo"
    ],
    "notes": [],
    "recipeInstructions": [
      "Coloque gelo até a metade da coqueteleira.",
      "Adicione o gin, o bénédictine e o suco de romã.",
      "Agite bem e coe pelo strainer, despejando apenas o líquido na taça.",
      "Decore com uma fatia de laranja."
    ],
    "image": "silent_siren.jpg"
  },
  {
    "id": 61,
    "name": "Sol Poente",
    "recipeCategory": "Alcoólico",
    "keywords": [
      "Refrescante"
    ],
    "serveIn": "Copo",
    "recipeCuisine": "Brasil",
    "recipeIngredient": [
      "25 ml de aperol",
      "50 ml de vodka",
      "80 ml de chá de hibisco",
      "40 ml de suco de laranja",
      "30 ml de mel",
      "Cubos de gelo",
      "Zeste de laranja"
    ],
    "notes": [],
    "recipeInstructions": [
      "Numa coqueteleira, coloque o Aperol e a vodka.",
      "Acrescente o chá de hibisco e o suco de laranja.",
      "Adicione o mel e complete com gelo.",
      "Agite bem e sirva com o gelo.",
      "Decore com o zeste de laranja."
    ],
    "image": "sol_poente.jpg"
  },
  {
    "id": 62,
    "name": "Tequila Sour",
    "recipeCategory": "Alcoólico",
    "keywords": [
      "Refrescante"
    ],
    "serveIn": "Copo",
    "recipeCuisine": "México",
    "recipeIngredient": [
      "1 ½ doses de tequila",
      "½ dose de suco de limão",
      "1 colher (sopa) de açúcar",
      "Cubos de gelo",
      "1 cereja marrasquino ou uma fatia de limão para decorar"
    ],
    "notes": [],
    "recipeInstructions": [
      "Encha a coqueteleira com gelo.",
      "Acrescente a tequila, o suco de limão e o açúcar.",
      "Agite bem, por cerca de 20 segundos.",
      "Coe com o strainer, despejando somente o líquido no copo.",
      "Decore com uma cereja marrasquino ou uma fatia de limão."
    ],
    "image": "tequila_sour.jpg"
  },
  {
    "id": 63,
    "name": "Tequila Sunrise",
    "recipeCategory": "Alcoólico",
    "keywords": [
      "Clássico",
      "Doce",
      "Gelado"
    ],
    "serveIn": "Taça",
    "recipeCuisine": "",
    "recipeIngredient": [
      "1 dose de tequila ouro",
      "3 doses de suco de laranja gelado",
      "Xarope de groselha",
      "1 fatia de laranja"
    ],
    "notes": [],
    "recipeInstructions": [
      "Despeje a dose de tequila diretamente no copo ou na taça e acrescente o suco de laranja.",
      "Misture bem com uma colher bailarina.",
      "Pingue algumas gotas de xarope de groselha e coloque uma fatia de laranja para decorar."
    ],
    "image": "tequila_sunrise.jpg"
  },
  {
    "id": 64,
    "name": "The Modernista",
    "recipeCategory": "Alcoólico",
    "keywords": [
      "Forte"
    ],
    "serveIn": "Taça De Coquetel",
    "recipeCuisine": "",
    "recipeIngredient": [
      "1 dose de uísque",
      "5 ml de absinto",
      "1 dose de rum ouro",
      "½ dose de suco de limão",
      "Angostura",
      "Cubos de gelo"
    ],
    "notes": [],
    "recipeInstructions": [
      "Coloque gelo até metade da coqueteleira.",
      "Acrescente o uísque, o absinto e o rum.",
      "Adicione o suco de limão e agite bem.",
      "Coe com o strainer, despejando apenas o líquido na taça."
    ],
    "image": "the_modernista.jpg"
  },
  {
    "id": 65,
    "name": "Vesper",
    "recipeCategory": "Alcoólico",
    "keywords": [
      "Clássico",
      "Forte",
      "Seco"
    ],
    "serveIn": "Taça De Coquetel",
    "recipeCuisine": "",
    "recipeIngredient": [
      "3 doses de gin",
      "1 dose de vodka",
      "1 ½ dose de Lillet Blanc",
      "Cubos de gelo"
    ],
    "notes": [],
    "recipeInstructions": [
      "Coloque gelo até a metade de uma coqueteleira.",
      "Acrescente o gin, a vodka e por fim o Lillet Blanc.",
      "Agite bem e coe pelo strainer, despejando apenas o líquido na taça.",
      "Decore com uma fatia fina e longa de casca de limão dentro do drink."
    ],
    "image": "vesper.jpg"
  },
  {
    "id": 66,
    "name": "Whisky Sour",
    "recipeCategory": "Alcoólico",
    "keywords": [
      "Refrescante"
    ],
    "serveIn": "Copo",
    "recipeCuisine": "",
    "recipeIngredient": [
      "1 dose de uísque",
      "⅔ de dose de suco de limão",
      "1 colher (chá) de açúcar",
      "Gelo picado"
    ],
    "notes": [],
    "recipeInstructions": [
      "Coloque o açúcar num prato.",
      "Molhe a borda do copo e vire-o contra o prato para preencher sua borda.",
      "Numa coqueteleira, coloque o gelo picado até sua metade.",
      "Acrescente o uísque, o suco de limão e o açúcar.",
      "Agite bem despeje no copo, coando com o strainer ou não.",
      "Decore com uma fatia de limão e uma cereja marrasquino."
    ],
    "image": "whisky_sour.jpg"
  },
  {
    "id": 67,
    "name": "White Russian",
    "recipeCategory": "Alcoólico",
    "keywords": [
      "Forte",
      "Cremoso"
    ],
    "serveIn": "Copo",
    "recipeCuisine": "",
    "recipeIngredient": [
      "2 doses de vodka",
      "1 dose de licor de café",
      "Creme de leite",
      "Cubos de gelo"
    ],
    "notes": [],
    "recipeInstructions": [
      "Encha o copo com gelo.",
      "Adicione a vodka e, sem seguida, o licor de café.",
      "Acrescente o creme de leite e mexa até que todos os ingredientes estejam misturados."
    ],
    "image": "white_russian.jpg"
  },
  {
    "id": 68,
    "name": "Woo Woo",
    "recipeCategory": "Alcoólico",
    "keywords": [
      "Refrescante"
    ],
    "serveIn": "Copo",
    "recipeCuisine": "",
    "recipeIngredient": [
      "2 doses de vodka",
      "1 dose de licor de pêssego",
      "4 doses de suco de cranberry",
      "Limão",
      "Cubos de gelo"
    ],
    "notes": [],
    "recipeInstructions": [
      "Encha ¾ do copo com gelo.",
      "Acrescente a vodka, o licor de pêssego e o suco de cranberry.",
      "Misture bem com uma colher bailarina e decore com uma fatia de limão."
    ],
    "image": "woo_woo.jpg"
  },
  {
    "id": 69,
    "name": "Xarope Simples",
    "recipeCategory": "",
    "keywords": [
      "Doce"
    ],
    "serveIn": "",
    "recipeCuisine": "",
    "recipeIngredient": [
      "1 parte de água",
      "1 parte de açúcar refinado"
    ],
    "notes": [],
    "recipeInstructions": [
      "Coloque o açúcar e a água em uma panela e leve ao fogo médio, mexendo até levantar fervura.",
      "Deixe cozinhar por cerca de 2 a 3 minutos até que o açúcar esteja totalmente diluído.",
      "Desligue o fogo e leve para a geladeira para resfriar."
    ],
    "image": "xarope_simples.jpg"
  },
  {
    "id": 70,
    "name": "Old Fashioned",
    "recipeCategory": "Alcoólico",
    "keywords": [
      "Clássico"
    ],
    "serveIn": "Copo",
    "recipeCuisine": "Estados Unidos",
    "recipeIngredient": [
      "½ colher (chá) de açúcar",
      "3 pitadas de angostura",
      "1 colher (chá) de água",
      "2 doses de bourbon",
      "Cubos de gelo",
      "Casca de laranja"
    ],
    "notes": [],
    "recipeInstructions": [
      "Coloque o açúcar e, em seguida, a angostura no copo.",
      "Adicione a água e então mexa com uma colher bailarina até que o açúcar esteja levemente dissolvido.",
      "Encha o copo com gelo, acrescentando o bourbon e mexendo gentilmente até que os ingredientes combinem.",
      "Passe um pouco da casca de laranja na borda do copo para soltar o óleo, jogando-a dentro dele."
    ],
    "image": "old_fashioned.jpg"
  },
  {
    "id": 71,
    "name": "Gibson",
    "recipeCategory": "Alcoólico",
    "keywords": [
      "Clássico",
      "Forte",
      "Seco",
      "Gelado"
    ],
    "serveIn": "Taça De Coquetel",
    "recipeCuisine": "Estados Unidos",
    "recipeIngredient": [
      "2½ doses de gin",
      "½ dose de vermute seco",
      "cubos de gelo",
      "cebolinhas em conserva"
    ],
    "notes": [],
    "recipeInstructions": [
      "Coloque gelo até a metade do mixing glass.",
      "Adicione overmute secoe o ginsobre o gelo e misture bem com umacolher bailarinaaté que os líquidos estejam bem gelados.",
      "Coe pelo strainer, despejando apenas o líquido na taça.",
      "Coloque trêscebolinhas em conservadentro da taça e sirva imediatamente."
    ],
    "image": "gibson.jpg"
  },
  {
    "id": 72,
    "name": "Carajillo 43",
    "recipeCategory": "Alcoólico",
    "keywords": [
      "Doce",
      "Amargo"
    ],
    "serveIn": "Copo",
    "recipeCuisine": "",
    "recipeIngredient": [
      "50ml de Licor 43",
      "50ml de café expresso quente",
      "Cubos de gelo"
    ],
    "notes": [],
    "recipeInstructions": [
      "Coloque 3 pedras de gelono copo.",
      "Adicione o Licor 43 por cima do gelo.",
      "Sirva com uma xícara de café expresso recém tirado.",
      "OCafé expressodeverá ser derramado dentro do copo no momento em que o drink for ser bebido."
    ],
    "image": "carajillo_43.jpg"
  }
]